MANIFEST.in
README.md
chk_alertes.py
comptage
comptage.py
comptage.service
comptage.sh
config.py
rf_temp_io
rf_temp_io.py
rf_temp_io.sh
setup.py
FERG/__init__.py
FERG/circuit.py
FERG/compteur_edf.py
FERG/fuel_tank.py
FERG/installation.py
FERG/tempeDB.py
FERG.egg-info/PKG-INFO
FERG.egg-info/SOURCES.txt
FERG.egg-info/dependency_links.txt
FERG.egg-info/top_level.txt
arduino/ferg_compt/ferg_compt.ino