Metadata-Version: 1.1
Name: FERG
Version: 0.9.5
Summary: Une bibliotheque pour Gerer - analyse les energies d'un maison individuelle
Home-page: UNKNOWN
Author: FredThx
Author-email: FredThx@gmail.com
License: WTFPL
Platform: UNKNOWN
Classifier: Programming Language :: Python
Classifier: Development Status :: 4 - Beta
Classifier: License :: OSI Approved
Classifier: Natural Language :: French
Classifier: Operating System :: OS Independent
Classifier: Programming Language :: Python :: 2.7
